{
    "24": {
        "becameSuitTime": 1665009299.241, 
        "savedBy": null, 
        "track": "c", 
        "numFloors": 1, 
        "difficulty": 2, 
        "state": "suit", 
        "block": 24
    }, 
    "25": {
        "becameSuitTime": 0, 
        "savedBy": null, 
        "track": "l", 
        "numFloors": 2, 
        "difficulty": 4, 
        "state": "toon", 
        "block": 25
    }, 
    "26": {
        "becameSuitTime": 0, 
        "savedBy": null, 
        "track": "c", 
        "numFloors": 1, 
        "difficulty": 1, 
        "state": "toon", 
        "block": 26
    }, 
    "20": {
        "becameSuitTime": 0, 
        "savedBy": null, 
        "track": "c", 
        "numFloors": 1, 
        "difficulty": 1, 
        "state": "toon", 
        "block": 20
    }, 
    "21": {
        "becameSuitTime": 0, 
        "savedBy": null, 
        "track": "c", 
        "numFloors": 1, 
        "difficulty": 1, 
        "state": "toon", 
        "block": 21
    }, 
    "23": {
        "becameSuitTime": 0, 
        "savedBy": null, 
        "track": "c", 
        "numFloors": 1, 
        "difficulty": 1, 
        "state": "toon", 
        "block": 23
    }, 
    "28": {
        "becameSuitTime": 0, 
        "savedBy": null, 
        "track": "c", 
        "numFloors": 1, 
        "difficulty": 1, 
        "state": "toon", 
        "block": 28
    }, 
    "29": {
        "becameSuitTime": 1663962066.262, 
        "savedBy": null, 
        "track": "s", 
        "numFloors": 1, 
        "difficulty": 6, 
        "state": "cogdo", 
        "block": 29
    }, 
    "2": {
        "becameSuitTime": 1665095294.395, 
        "savedBy": null, 
        "track": "s", 
        "numFloors": 2, 
        "difficulty": 4, 
        "state": "suit", 
        "block": 2
    }, 
    "5": {
        "becameSuitTime": 0, 
        "savedBy": null, 
        "track": "c", 
        "numFloors": 1, 
        "difficulty": 1, 
        "state": "toon", 
        "block": 5
    }, 
    "4": {
        "becameSuitTime": 1663971093.276, 
        "savedBy": null, 
        "track": "s", 
        "numFloors": 1, 
        "difficulty": 6, 
        "state": "cogdo", 
        "block": 4
    }, 
    "7": {
        "becameSuitTime": 1663962171.229, 
        "savedBy": null, 
        "track": "l", 
        "numFloors": 2, 
        "difficulty": 6, 
        "state": "cogdo", 
        "block": 7
    }, 
    "6": {
        "becameSuitTime": 0, 
        "savedBy": null, 
        "track": "c", 
        "numFloors": 1, 
        "difficulty": 1, 
        "state": "toon", 
        "block": 6
    }, 
    "9": {
        "becameSuitTime": 1663971148.934, 
        "savedBy": null, 
        "track": "s", 
        "numFloors": 1, 
        "difficulty": 6, 
        "state": "cogdo", 
        "block": 9
    }, 
    "8": {
        "becameSuitTime": 0, 
        "savedBy": null, 
        "track": "c", 
        "numFloors": 1, 
        "difficulty": 1, 
        "state": "toon", 
        "block": 8
    }, 
    "11": {
        "becameSuitTime": 0, 
        "savedBy": null, 
        "track": "l", 
        "numFloors": 1, 
        "difficulty": 2, 
        "state": "toon", 
        "block": 11
    }, 
    "10": {
        "becameSuitTime": 1663971031.743, 
        "savedBy": null, 
        "track": "l", 
        "numFloors": 3, 
        "difficulty": 5, 
        "state": "suit", 
        "block": 10
    }, 
    "13": {
        "becameSuitTime": 1663971332.657, 
        "savedBy": null, 
        "track": "l", 
        "numFloors": 1, 
        "difficulty": 2, 
        "state": "suit", 
        "block": 13
    }, 
    "15": {
        "becameSuitTime": 1663971073.745, 
        "savedBy": null, 
        "track": "l", 
        "numFloors": 2, 
        "difficulty": 6, 
        "state": "cogdo", 
        "block": 15
    }, 
    "14": {
        "becameSuitTime": 1663971182.758, 
        "savedBy": null, 
        "track": "s", 
        "numFloors": 1, 
        "difficulty": 6, 
        "state": "cogdo", 
        "block": 14
    }, 
    "19": {
        "becameSuitTime": 0, 
        "savedBy": null, 
        "track": "c", 
        "numFloors": 1, 
        "difficulty": 1, 
        "state": "toon", 
        "block": 19
    }, 
    "18": {
        "becameSuitTime": 0, 
        "savedBy": null, 
        "track": "c", 
        "numFloors": 1, 
        "difficulty": 1, 
        "state": "toon", 
        "block": 18
    }, 
    "31": {
        "becameSuitTime": 0, 
        "savedBy": null, 
        "track": "c", 
        "numFloors": 1, 
        "difficulty": 1, 
        "state": "toon", 
        "block": 31
    }, 
    "30": {
        "becameSuitTime": 0, 
        "savedBy": null, 
        "track": "c", 
        "numFloors": 1, 
        "difficulty": 1, 
        "state": "toon", 
        "block": 30
    }, 
    "34": {
        "becameSuitTime": 0, 
        "savedBy": null, 
        "track": "c", 
        "numFloors": 1, 
        "difficulty": 1, 
        "state": "toon", 
        "block": 34
    }, 
    "33": {
        "becameSuitTime": 0, 
        "savedBy": null, 
        "track": "c", 
        "numFloors": 1, 
        "difficulty": 1, 
        "state": "toon", 
        "block": 33
    }, 
    "32": {
        "becameSuitTime": 1665009003.706, 
        "savedBy": null, 
        "track": "c", 
        "numFloors": 1, 
        "difficulty": 2, 
        "state": "suit", 
        "block": 32
    }
}